portobello/__init__.py
portobello/cli.py
portobello/internal/__init__.py
portobello/internal/template_config.json
portobello/internal/utils.py
portobello/ldap/__init__.py
portobello/ldap/main.py
portobello/netstat/__init__.py
portobello/netstat/main.py
portobello-0.5.4.dist-info/METADATA
portobello-0.5.4.dist-info/WHEEL
portobello-0.5.4.dist-info/entry_points.txt
portobello-0.5.4.dist-info/licenses/LICENSE
portobello-0.5.4.dist-info/RECORD
