Metadata-Version: 2.3
Name: portobello
Version: 0.5.4
Summary: Python package for various helpful CLI utilities.
Project-URL: Homepage, https://github.com/nommu-moose/portobello
Project-URL: Bug Tracker, https://github.com/nommu-moose/portobello/issues
Author-email: Cameron Fazakerley <moose@nommumail.co.uk>
License:                     GNU GENERAL PUBLIC LICENSE
License-File: LICENSE
Classifier: License :: OSI Approved :: GNU General Public License v3 (GPLv3)
Classifier: Operating System :: OS Independent
Classifier: Programming Language :: Python :: 3
Requires-Python: >=3.8
Requires-Dist: ldap3
Requires-Dist: psutil
Requires-Dist: pykeepass
